ietflinks/__init__.py
ietflinks/main.py
ietflinks/py.typed
ietflinks/data/field-names.csv
pymdown_ietflinks-0.0.0.dist-info/METADATA
pymdown_ietflinks-0.0.0.dist-info/WHEEL
pymdown_ietflinks-0.0.0.dist-info/entry_points.txt
pymdown_ietflinks-0.0.0.dist-info/licenses/AUTHORS.md
pymdown_ietflinks-0.0.0.dist-info/licenses/LICENSE
pymdown_ietflinks-0.0.0.dist-info/RECORD
