Metadata-Version: 2.3
Name: pymdown-ietflinks
Version: 0.0.0
Summary: Easily link to IETF documentation from within MarkDown
Project-URL: Source Code, https://github.com/dave-shawley/pymdown-ietf
Author-email: Dave Shawley <daveshawley@gmail.com>
License: Copyright (c) 2024, Dave Shawley
Classifier: Development Status :: 1 - Planning
Classifier: Intended Audience :: Developers
Classifier: License :: OSI Approved :: BSD License
Classifier: Operating System :: OS Independent
Classifier: Programming Language :: Python
Classifier: Programming Language :: Python :: 3
Classifier: Programming Language :: Python :: 3.12
Classifier: Programming Language :: Python :: 3.13
Classifier: Topic :: Text Processing
Classifier: Typing :: Typed
Requires-Python: >=3.12
Requires-Dist: markdown<4,>=3.7
